setup.py
py_func_openapi/__init__.py
py_func_openapi/openapi_parser.py
py_func_openapi.egg-info/PKG-INFO
py_func_openapi.egg-info/SOURCES.txt
py_func_openapi.egg-info/dependency_links.txt
py_func_openapi.egg-info/top_level.txt