Metadata-Version: 2.1
Name: py-func-openapi
Version: 0.0.3
Summary: A simple tool to generate openapi json from python function
Home-page: https://pypi.org/project/py-func-openapi/
Author: chendefine
Author-email: chendefine@gmail.com
